{
  "date": "20260504",
  "place": "佐賀",
  "place_code": "32",
  "title": "2026.05.04 佐賀競馬 予想",
  "predictions": [
    {
      "race_no": 1,
      "race_name": "３歳-７組",
      "picks": [
        {
          "mark": "◎",
          "umaban": 5,
          "name": "ニシノナスタチウム",
          "score": 62.56,
          "sp": 57.2,
          "base_index": 100.0,
          "jockey": "長田進",
          "jockey_add": 2.93375,
          "z": {
            "sp": 1.3632233046947482,
            "kb": 1.6336968865861805,
            "jockey": -0.22362426039831515,
            "combined": 1.2560864093577502,
            "norm_method": "z"
          },
          "source": {
            "kichiuma_fp_url": "https://www.kichiuma-chiho.net/php/search.php?race_id=202605040132&date=2026%2F5%2F4&no=1&id=32&p=fp",
            "nar_table_url": "https://nar.k-ba.net/table.php?date=20260504&track=32&number=1&condition=1",
            "nar_condition": "1"
          }
        },
        {
          "mark": "〇",
          "umaban": 4,
          "name": "スピネルテソーロ",
          "score": 57.84,
          "sp": 57.2,
          "base_index": 84.0,
          "jockey": "中山蓮",
          "jockey_add": 2.5650000000000004,
          "z": {
            "sp": 1.3632233046947482,
            "kb": 0.11397885255252448,
            "jockey": -0.44005850192555546,
            "combined": 0.7836476650505291,
            "norm_method": "z"
          },
          "source": {
            "kichiuma_fp_url": "https://www.kichiuma-chiho.net/php/search.php?race_id=202605040132&date=2026%2F5%2F4&no=1&id=32&p=fp",
            "nar_table_url": "https://nar.k-ba.net/table.php?date=20260504&track=32&number=1&condition=1",
            "nar_condition": "1"
          }
        },
        {
          "mark": "▲",
          "umaban": 3,
          "name": "ボンスヴニール",
          "score": 55.65,
          "sp": 52.1,
          "base_index": 93.0,
          "jockey": "出水拓",
          "jockey_add": 3.8425000000000002,
          "z": {
            "sp": 0.41343657601398165,
            "kb": 0.968820246696456,
            "jockey": 0.3097577517722068,
            "combined": 0.564587205715677,
            "norm_method": "z"
          },
          "source": {
            "kichiuma_fp_url": "https://www.kichiuma-chiho.net/php/search.php?race_id=202605040132&date=2026%2F5%2F4&no=1&id=32&p=fp",
            "nar_table_url": "https://nar.k-ba.net/table.php?date=20260504&track=32&number=1&condition=1",
            "nar_condition": "1"
          }
        },
        {
          "mark": "△",
          "umaban": 2,
          "name": "ブリックヤード",
          "score": 54.79,
          "sp": 54.0,
          "base_index": 92.0,
          "jockey": "長谷蓮",
          "jockey_add": 0.0,
          "z": {
            "sp": 0.7672786906205413,
            "kb": 0.8738378695693525,
            "jockey": -1.945560412481141,
            "combined": 0.4794620840641114,
            "norm_method": "z"
          },
          "source": {
            "kichiuma_fp_url": "https://www.kichiuma-chiho.net/php/search.php?race_id=202605040132&date=2026%2F5%2F4&no=1&id=32&p=fp",
            "nar_table_url": "https://nar.k-ba.net/table.php?date=20260504&track=32&number=1&condition=1",
            "nar_condition": "1"
          }
        },
        {
          "mark": "☆",
          "umaban": 7,
          "name": "ライフイズマネー",
          "score": 53.21,
          "sp": 50.8,
          "base_index": 88.0,
          "jockey": "竹吉徹",
          "jockey_add": 4.405,
          "z": {
            "sp": 0.1713340765463346,
            "kb": 0.4939083610609385,
            "jockey": 0.6399116795256247,
            "combined": 0.3213356429305464,
            "norm_method": "z"
          },
          "source": {
            "kichiuma_fp_url": "https://www.kichiuma-chiho.net/php/search.php?race_id=202605040132&date=2026%2F5%2F4&no=1&id=32&p=fp",
            "nar_table_url": "https://nar.k-ba.net/table.php?date=20260504&track=32&number=1&condition=1",
            "nar_condition": "1"
          }
        }
      ],
      "konsen": {
        "name": "混戦度",
        "value": 17.9,
        "is_focus": false,
        "gap12": 4.72,
        "gap15": 9.35,
        "gap12_mid": 0.8,
        "gap15_mid": 3.0,
        "focus_th": 30.0,
        "sc12": 0.1449,
        "sc15": 0.2429
      }
    },
    {
      "race_no": 2,
      "race_name": "３歳-６組",
      "picks": [
        {
          "mark": "◎",
          "umaban": 5,
          "name": "キャプテンレガーロ",
          "score": 63.75,
          "sp": 69.42307692307692,
          "base_index": 93.0,
          "jockey": "山口勲",
          "jockey_add": 8.65,
          "z": {
            "sp": 1.3268140401443123,
            "kb": 1.3268140401443131,
            "jockey": 1.7331249774351276,
            "combined": 1.3746153268844084,
            "norm_method": "z"
          },
          "source": {
            "kichiuma_fp_url": "https://www.kichiuma-chiho.net/php/search.php?race_id=202605040232&date=2026%2F5%2F4&no=2&id=32&p=fp",
            "nar_table_url": "https://nar.k-ba.net/table.php?date=20260504&track=32&number=2&condition=1",
            "nar_condition": "1"
          }
        },
        {
          "mark": "〇",
          "umaban": 6,
          "name": "スフェーンテソーロ",
          "score": 63.61,
          "sp": 70.0,
          "base_index": 94.0,
          "jockey": "飛田愛",
          "jockey_add": 6.625,
          "z": {
            "sp": 1.4229599850823065,
            "kb": 1.422959985082307,
            "jockey": 0.8926584554196494,
            "combined": 1.3605715698278764,
            "norm_method": "z"
          },
          "source": {
            "kichiuma_fp_url": "https://www.kichiuma-chiho.net/php/search.php?race_id=202605040232&date=2026%2F5%2F4&no=2&id=32&p=fp",
            "nar_table_url": "https://nar.k-ba.net/table.php?date=20260504&track=32&number=2&condition=1",
            "nar_condition": "1"
          }
        },
        {
          "mark": "▲",
          "umaban": 7,
          "name": "ユイアヴェニール",
          "score": 60.37,
          "sp": 70.0,
          "base_index": 94.0,
          "jockey": "長谷蓮",
          "jockey_add": 0.0,
          "z": {
            "sp": 1.4229599850823065,
            "kb": 1.422959985082307,
            "jockey": -1.8570159684581495,
            "combined": 1.0370804611363706,
            "norm_method": "z"
          },
          "source": {
            "kichiuma_fp_url": "https://www.kichiuma-chiho.net/php/search.php?race_id=202605040232&date=2026%2F5%2F4&no=2&id=32&p=fp",
            "nar_table_url": "https://nar.k-ba.net/table.php?date=20260504&track=32&number=2&condition=1",
            "nar_condition": "1"
          }
        },
        {
          "mark": "△",
          "umaban": 3,
          "name": "メロディセーラ",
          "score": 48.46,
          "sp": 60.76923076923077,
          "base_index": 78.0,
          "jockey": "加茂飛",
          "jockey_add": 3.3999999999999995,
          "z": {
            "sp": -0.11537513392559386,
            "kb": -0.11537513392559275,
            "jockey": -0.4458623018642605,
            "combined": -0.1542559772124955,
            "norm_method": "z"
          },
          "source": {
            "kichiuma_fp_url": "https://www.kichiuma-chiho.net/php/search.php?race_id=202605040232&date=2026%2F5%2F4&no=2&id=32&p=fp",
            "nar_table_url": "https://nar.k-ba.net/table.php?date=20260504&track=32&number=2&condition=1",
            "nar_condition": "1"
          }
        },
        {
          "mark": "☆",
          "umaban": 4,
          "name": "ダッテウマダモノ",
          "score": 46.53,
          "sp": 59.61538461538461,
          "base_index": 76.0,
          "jockey": "長田進",
          "jockey_add": 2.93375,
          "z": {
            "sp": -0.3076670238015813,
            "kb": -0.3076670238015802,
            "jockey": -0.6393771245258488,
            "combined": -0.34669174153384774,
            "norm_method": "z"
          },
          "source": {
            "kichiuma_fp_url": "https://www.kichiuma-chiho.net/php/search.php?race_id=202605040232&date=2026%2F5%2F4&no=2&id=32&p=fp",
            "nar_table_url": "https://nar.k-ba.net/table.php?date=20260504&track=32&number=2&condition=1",
            "nar_condition": "1"
          }
        }
      ],
      "konsen": {
        "name": "混戦度",
        "value": 60.5,
        "is_focus": true,
        "gap12": 0.14,
        "gap15": 17.22,
        "gap12_mid": 0.8,
        "gap15_mid": 3.0,
        "focus_th": 30.0,
        "sc12": 0.8511,
        "sc15": 0.1484
      }
    },
    {
      "race_no": 3,
      "race_name": "サガデーナイト競馬パドックリニューアル記念Ｃ２-１０組",
      "picks": [
        {
          "mark": "◎",
          "umaban": 7,
          "name": "ピエナクレスコ",
          "score": 74.07,
          "sp": 70.9,
          "base_index": 116.0,
          "jockey": "飛田愛",
          "jockey_add": 6.625,
          "z": {
            "sp": 2.577506988168962,
            "kb": 2.5390481860221032,
            "jockey": 1.222701525954528,
            "combined": 2.406806697865246,
            "norm_method": "z"
          },
          "source": {
            "kichiuma_fp_url": "https://www.kichiuma-chiho.net/php/search.php?race_id=202605040332&date=2026%2F5%2F4&no=3&id=32&p=fp",
            "nar_table_url": "https://nar.k-ba.net/table.php?date=20260504&track=32&number=3&condition=1",
            "nar_condition": "1"
          }
        },
        {
          "mark": "〇",
          "umaban": 2,
          "name": "ルミナスフラックス",
          "score": 58.42,
          "sp": 60.1,
          "base_index": 96.0,
          "jockey": "山口勲",
          "jockey_add": 8.65,
          "z": {
            "sp": 0.6919907923901906,
            "kb": 0.6325956231386131,
            "jockey": 2.116663746137094,
            "combined": 0.8421302077570094,
            "norm_method": "z"
          },
          "source": {
            "kichiuma_fp_url": "https://www.kichiuma-chiho.net/php/search.php?race_id=202605040332&date=2026%2F5%2F4&no=3&id=32&p=fp",
            "nar_table_url": "https://nar.k-ba.net/table.php?date=20260504&track=32&number=3&condition=1",
            "nar_condition": "1"
          }
        },
        {
          "mark": "▲",
          "umaban": 4,
          "name": "リンガスマイル",
          "score": 51.29,
          "sp": 57.2,
          "base_index": 91.0,
          "jockey": "田中直",
          "jockey_add": 3.3449999999999998,
          "z": {
            "sp": 0.18569477685700242,
            "kb": 0.1559824824177405,
            "jockey": -0.2252965393288386,
            "combined": 0.1286039471765323,
            "norm_method": "z"
          },
          "source": {
            "kichiuma_fp_url": "https://www.kichiuma-chiho.net/php/search.php?race_id=202605040332&date=2026%2F5%2F4&no=3&id=32&p=fp",
            "nar_table_url": "https://nar.k-ba.net/table.php?date=20260504&track=32&number=3&condition=1",
            "nar_condition": "1"
          }
        },
        {
          "mark": "△",
          "umaban": 1,
          "name": "エイシントレボン",
          "score": 50.09,
          "sp": 57.8,
          "base_index": 87.0,
          "jockey": "青海大",
          "jockey_add": 2.01875,
          "z": {
            "sp": 0.29044567662248866,
            "kb": -0.2253080301589576,
            "jockey": -0.8107866106953218,
            "combined": 0.00919667023761499,
            "norm_method": "z"
          },
          "source": {
            "kichiuma_fp_url": "https://www.kichiuma-chiho.net/php/search.php?race_id=202605040332&date=2026%2F5%2F4&no=3&id=32&p=fp",
            "nar_table_url": "https://nar.k-ba.net/table.php?date=20260504&track=32&number=3&condition=1",
            "nar_condition": "1"
          }
        },
        {
          "mark": "☆",
          "umaban": 6,
          "name": "ビヨンドザバラード",
          "score": 49.91,
          "sp": 55.9,
          "base_index": 90.0,
          "jockey": "金山昇",
          "jockey_add": 3.8012500000000005,
          "z": {
            "sp": -0.04126550596822069,
            "kb": 0.060659854273565975,
            "jockey": -0.023879125522272462,
            "combined": -0.009242002315230704,
            "norm_method": "z"
          },
          "source": {
            "kichiuma_fp_url": "https://www.kichiuma-chiho.net/php/search.php?race_id=202605040332&date=2026%2F5%2F4&no=3&id=32&p=fp",
            "nar_table_url": "https://nar.k-ba.net/table.php?date=20260504&track=32&number=3&condition=1",
            "nar_condition": "1"
          }
        }
      ],
      "konsen": {
        "name": "混戦度",
        "value": 7.0,
        "is_focus": false,
        "gap12": 15.65,
        "gap15": 24.16,
        "gap12_mid": 0.8,
        "gap15_mid": 3.0,
        "focus_th": 30.0,
        "sc12": 0.0486,
        "sc15": 0.1105
      }
    },
    {
      "race_no": 4,
      "race_name": "Ｃ２-９組",
      "picks": [
        {
          "mark": "◎",
          "umaban": 12,
          "name": "ライフク",
          "score": 69.03,
          "sp": 70.0,
          "base_index": 107.0,
          "jockey": "山口勲",
          "jockey_add": 8.65,
          "z": {
            "sp": 1.870828693386969,
            "kb": 1.8708286933869707,
            "jockey": 2.145255262384501,
            "combined": 1.9031141720925615,
            "norm_method": "z"
          },
          "source": {
            "kichiuma_fp_url": "https://www.kichiuma-chiho.net/php/search.php?race_id=202605040432&date=2026%2F5%2F4&no=4&id=32&p=fp",
            "nar_table_url": "https://nar.k-ba.net/table.php?date=20260504&track=32&number=4&condition=1",
            "nar_condition": "1"
          }
        },
        {
          "mark": "〇",
          "umaban": 11,
          "name": "ムコリッタ",
          "score": 56.84,
          "sp": 64.47368421052632,
          "base_index": 100.0,
          "jockey": "飛田愛",
          "jockey_add": 6.625,
          "z": {
            "sp": 0.623609564462322,
            "kb": 0.6236095644623235,
            "jockey": 1.1376746317791686,
            "combined": 0.684087807676069,
            "norm_method": "z"
          },
          "source": {
            "kichiuma_fp_url": "https://www.kichiuma-chiho.net/php/search.php?race_id=202605040432&date=2026%2F5%2F4&no=4&id=32&p=fp",
            "nar_table_url": "https://nar.k-ba.net/table.php?date=20260504&track=32&number=4&condition=1",
            "nar_condition": "1"
          }
        },
        {
          "mark": "▲",
          "umaban": 4,
          "name": "カイブルーノ",
          "score": 56.56,
          "sp": 65.26315789473685,
          "base_index": 101.0,
          "jockey": "川島拓",
          "jockey_add": 3.455,
          "z": {
            "sp": 0.8017837257372734,
            "kb": 0.8017837257372732,
            "jockey": -0.439624429464734,
            "combined": 0.6557357074782136,
            "norm_method": "z"
          },
          "source": {
            "kichiuma_fp_url": "https://www.kichiuma-chiho.net/php/search.php?race_id=202605040432&date=2026%2F5%2F4&no=4&id=32&p=fp",
            "nar_table_url": "https://nar.k-ba.net/table.php?date=20260504&track=32&number=4&condition=1",
            "nar_condition": "1"
          }
        },
        {
          "mark": "△",
          "umaban": 6,
          "name": "ユイダイナソー",
          "score": 55.54,
          "sp": 64.47368421052632,
          "base_index": 100.0,
          "jockey": "竹吉徹",
          "jockey_add": 4.405,
          "z": {
            "sp": 0.623609564462322,
            "kb": 0.6236095644623235,
            "jockey": 0.03306771822665645,
            "combined": 0.5541340531404794,
            "norm_method": "z"
          },
          "source": {
            "kichiuma_fp_url": "https://www.kichiuma-chiho.net/php/search.php?race_id=202605040432&date=2026%2F5%2F4&no=4&id=32&p=fp",
            "nar_table_url": "https://nar.k-ba.net/table.php?date=20260504&track=32&number=4&condition=1",
            "nar_condition": "1"
          }
        },
        {
          "mark": "☆",
          "umaban": 1,
          "name": "シリウスライト",
          "score": 55.41,
          "sp": 63.68421052631579,
          "base_index": 99.0,
          "jockey": "石川慎",
          "jockey_add": 6.865,
          "z": {
            "sp": 0.4454354031873722,
            "kb": 0.44543540318737396,
            "jockey": 1.2570915954064672,
            "combined": 0.5409243669778545,
            "norm_method": "z"
          },
          "source": {
            "kichiuma_fp_url": "https://www.kichiuma-chiho.net/php/search.php?race_id=202605040432&date=2026%2F5%2F4&no=4&id=32&p=fp",
            "nar_table_url": "https://nar.k-ba.net/table.php?date=20260504&track=32&number=4&condition=1",
            "nar_condition": "1"
          }
        }
      ],
      "konsen": {
        "name": "混戦度",
        "value": 10.3,
        "is_focus": false,
        "gap12": 12.19,
        "gap15": 13.62,
        "gap12_mid": 0.8,
        "gap15_mid": 3.0,
        "focus_th": 30.0,
        "sc12": 0.0616,
        "sc15": 0.1805
      }
    },
    {
      "race_no": 5,
      "race_name": "Ｃ２-８組",
      "picks": [
        {
          "mark": "◎",
          "umaban": 6,
          "name": "ミシャベル",
          "score": 59.76,
          "sp": 57.5,
          "base_index": 98.0,
          "jockey": "林悠翔",
          "jockey_add": 3.61125,
          "z": {
            "sp": 1.064132754243763,
            "kb": 1.1963839780037124,
            "jockey": -0.01217186998229153,
            "combined": 0.9764060995583299,
            "norm_method": "z"
          },
          "source": {
            "kichiuma_fp_url": "https://www.kichiuma-chiho.net/php/search.php?race_id=202605040532&date=2026%2F5%2F4&no=5&id=32&p=fp",
            "nar_table_url": "https://nar.k-ba.net/table.php?date=20260504&track=32&number=5&condition=1",
            "nar_condition": "1"
          }
        },
        {
          "mark": "〇",
          "umaban": 5,
          "name": "ニンマリ",
          "score": 59.42,
          "sp": 58.1,
          "base_index": 97.0,
          "jockey": "長田進",
          "jockey_add": 2.93375,
          "z": {
            "sp": 1.166812230530442,
            "kb": 1.0185431164085663,
            "jockey": -0.3714228048061635,
            "combined": 0.9422348398667605,
            "norm_method": "z"
          },
          "source": {
            "kichiuma_fp_url": "https://www.kichiuma-chiho.net/php/search.php?race_id=202605040532&date=2026%2F5%2F4&no=5&id=32&p=fp",
            "nar_table_url": "https://nar.k-ba.net/table.php?date=20260504&track=32&number=5&condition=1",
            "nar_condition": "1"
          }
        },
        {
          "mark": "▲",
          "umaban": 11,
          "name": "タガノミモザ",
          "score": 58.39,
          "sp": 56.2,
          "base_index": 94.0,
          "jockey": "石川慎",
          "jockey_add": 6.865,
          "z": {
            "sp": 0.841660555622626,
            "kb": 0.48502053162312736,
            "jockey": 1.713160571616488,
            "combined": 0.8392958445632278,
            "norm_method": "z"
          },
          "source": {
            "kichiuma_fp_url": "https://www.kichiuma-chiho.net/php/search.php?race_id=202605040532&date=2026%2F5%2F4&no=5&id=32&p=fp",
            "nar_table_url": "https://nar.k-ba.net/table.php?date=20260504&track=32&number=5&condition=1",
            "nar_condition": "1"
          }
        },
        {
          "mark": "△",
          "umaban": 8,
          "name": "サトノシュタール",
          "score": 57.64,
          "sp": 55.6,
          "base_index": 94.0,
          "jockey": "飛田愛",
          "jockey_add": 6.625,
          "z": {
            "sp": 0.7389810793359468,
            "kb": 0.48502053162312736,
            "jockey": 1.5858982478412418,
            "combined": 0.7639241145386817,
            "norm_method": "z"
          },
          "source": {
            "kichiuma_fp_url": "https://www.kichiuma-chiho.net/php/search.php?race_id=202605040532&date=2026%2F5%2F4&no=5&id=32&p=fp",
            "nar_table_url": "https://nar.k-ba.net/table.php?date=20260504&track=32&number=5&condition=1",
            "nar_condition": "1"
          }
        },
        {
          "mark": "☆",
          "umaban": 9,
          "name": "ディーズミソロジー",
          "score": 51.19,
          "sp": 51.1,
          "base_index": 95.0,
          "jockey": "小松丈",
          "jockey_add": 2.71,
          "z": {
            "sp": -0.031114992814144784,
            "kb": 0.6628613932182736,
            "jockey": -0.4900684087424606,
            "combined": 0.11900118943911761,
            "norm_method": "z"
          },
          "source": {
            "kichiuma_fp_url": "https://www.kichiuma-chiho.net/php/search.php?race_id=202605040532&date=2026%2F5%2F4&no=5&id=32&p=fp",
            "nar_table_url": "https://nar.k-ba.net/table.php?date=20260504&track=32&number=5&condition=1",
            "nar_condition": "1"
          }
        }
      ],
      "konsen": {
        "name": "混戦度",
        "value": 54.7,
        "is_focus": true,
        "gap12": 0.34,
        "gap15": 8.57,
        "gap12_mid": 0.8,
        "gap15_mid": 3.0,
        "focus_th": 30.0,
        "sc12": 0.7018,
        "sc15": 0.2593
      }
    },
    {
      "race_no": 6,
      "race_name": "Ｃ１-９組",
      "picks": [
        {
          "mark": "◎",
          "umaban": 3,
          "name": "レクエルド",
          "score": 63.08,
          "sp": 70.0,
          "base_index": 109.0,
          "jockey": "出水拓",
          "jockey_add": 3.8425000000000002,
          "z": {
            "sp": 1.5150844700898267,
            "kb": 1.5150844700898265,
            "jockey": -0.243950453691014,
            "combined": 1.3081391849391395,
            "norm_method": "z"
          },
          "source": {
            "kichiuma_fp_url": "https://www.kichiuma-chiho.net/php/search.php?race_id=202605040632&date=2026%2F5%2F4&no=6&id=32&p=fp",
            "nar_table_url": "https://nar.k-ba.net/table.php?date=20260504&track=32&number=6&condition=1",
            "nar_condition": "1"
          }
        },
        {
          "mark": "〇",
          "umaban": 2,
          "name": "オールズフェア",
          "score": 59.09,
          "sp": 67.5,
          "base_index": 106.0,
          "jockey": "飛田愛",
          "jockey_add": 6.625,
          "z": {
            "sp": 0.9178978906383625,
            "kb": 0.9178978906383624,
            "jockey": 0.8430832182942561,
            "combined": 0.9090961644802323,
            "norm_method": "z"
          },
          "source": {
            "kichiuma_fp_url": "https://www.kichiuma-chiho.net/php/search.php?race_id=202605040632&date=2026%2F5%2F4&no=6&id=32&p=fp",
            "nar_table_url": "https://nar.k-ba.net/table.php?date=20260504&track=32&number=6&condition=1",
            "nar_condition": "1"
          }
        },
        {
          "mark": "▲",
          "umaban": 4,
          "name": "リヨン",
          "score": 52.36,
          "sp": 65.0,
          "base_index": 103.0,
          "jockey": "川島拓",
          "jockey_add": 3.455,
          "z": {
            "sp": 0.3207113111868981,
            "kb": 0.3207113111868981,
            "jockey": -0.39533429839695916,
            "combined": 0.2364706512358561,
            "norm_method": "z"
          },
          "source": {
            "kichiuma_fp_url": "https://www.kichiuma-chiho.net/php/search.php?race_id=202605040632&date=2026%2F5%2F4&no=6&id=32&p=fp",
            "nar_table_url": "https://nar.k-ba.net/table.php?date=20260504&track=32&number=6&condition=1",
            "nar_condition": "1"
          }
        },
        {
          "mark": "△",
          "umaban": 5,
          "name": "フェルカド",
          "score": 52.13,
          "sp": 65.0,
          "base_index": 103.0,
          "jockey": "長田進",
          "jockey_add": 2.93375,
          "z": {
            "sp": 0.3207113111868981,
            "kb": 0.3207113111868981,
            "jockey": -0.5989699862756015,
            "combined": 0.21251351148542758,
            "norm_method": "z"
          },
          "source": {
            "kichiuma_fp_url": "https://www.kichiuma-chiho.net/php/search.php?race_id=202605040632&date=2026%2F5%2F4&no=6&id=32&p=fp",
            "nar_table_url": "https://nar.k-ba.net/table.php?date=20260504&track=32&number=6&condition=1",
            "nar_condition": "1"
          }
        },
        {
          "mark": "☆",
          "umaban": 8,
          "name": "セイスカーレット",
          "score": 49.8,
          "sp": 63.75,
          "base_index": 101.5,
          "jockey": "林悠翔",
          "jockey_add": 3.61125,
          "z": {
            "sp": 0.022118021461165975,
            "kb": 0.02211802146116597,
            "jockey": -0.3342924255316587,
            "combined": -0.019812619361519287,
            "norm_method": "z"
          },
          "source": {
            "kichiuma_fp_url": "https://www.kichiuma-chiho.net/php/search.php?race_id=202605040632&date=2026%2F5%2F4&no=6&id=32&p=fp",
            "nar_table_url": "https://nar.k-ba.net/table.php?date=20260504&track=32&number=6&condition=1",
            "nar_condition": "1"
          }
        }
      ],
      "konsen": {
        "name": "混戦度",
        "value": 17.3,
        "is_focus": false,
        "gap12": 3.99,
        "gap15": 13.28,
        "gap12_mid": 0.8,
        "gap15_mid": 3.0,
        "focus_th": 30.0,
        "sc12": 0.167,
        "sc15": 0.1843
      }
    },
    {
      "race_no": 7,
      "race_name": "Ｃ１-８組",
      "picks": [
        {
          "mark": "◎",
          "umaban": 9,
          "name": "チカポコ",
          "score": 67.76,
          "sp": 70.0,
          "base_index": 102.0,
          "jockey": "出水拓",
          "jockey_add": 3.8425000000000002,
          "z": {
            "sp": 2.0046226471544464,
            "kb": 2.0046226471544446,
            "jockey": 0.06058911613122145,
            "combined": 1.775912819975243,
            "norm_method": "z"
          },
          "source": {
            "kichiuma_fp_url": "https://www.kichiuma-chiho.net/php/search.php?race_id=202605040732&date=2026%2F5%2F4&no=7&id=32&p=fp",
            "nar_table_url": "https://nar.k-ba.net/table.php?date=20260504&track=32&number=7&condition=1",
            "nar_condition": "1"
          }
        },
        {
          "mark": "〇",
          "umaban": 5,
          "name": "ミスレモン",
          "score": 55.47,
          "sp": 62.5,
          "base_index": 96.0,
          "jockey": "飛田愛",
          "jockey_add": 6.625,
          "z": {
            "sp": 0.31057533969998463,
            "kb": 0.310575339699983,
            "jockey": 2.3159632383402107,
            "combined": 0.5465033277753049,
            "norm_method": "z"
          },
          "source": {
            "kichiuma_fp_url": "https://www.kichiuma-chiho.net/php/search.php?race_id=202605040732&date=2026%2F5%2F4&no=7&id=32&p=fp",
            "nar_table_url": "https://nar.k-ba.net/table.php?date=20260504&track=32&number=7&condition=1",
            "nar_condition": "1"
          }
        },
        {
          "mark": "▲",
          "umaban": 10,
          "name": "スパーキングブルー",
          "score": 53.17,
          "sp": 62.5,
          "base_index": 96.0,
          "jockey": "山下裕",
          "jockey_add": 4.22,
          "z": {
            "sp": 0.31057533969998463,
            "kb": 0.310575339699983,
            "jockey": 0.36657428455310553,
            "combined": 0.3171634508591749,
            "norm_method": "z"
          },
          "source": {
            "kichiuma_fp_url": "https://www.kichiuma-chiho.net/php/search.php?race_id=202605040732&date=2026%2F5%2F4&no=7&id=32&p=fp",
            "nar_table_url": "https://nar.k-ba.net/table.php?date=20260504&track=32&number=7&condition=1",
            "nar_condition": "1"
          }
        },
        {
          "mark": "△",
          "umaban": 8,
          "name": "アーコレード",
          "score": 52.77,
          "sp": 62.5,
          "base_index": 96.0,
          "jockey": "金山昇",
          "jockey_add": 3.8012500000000005,
          "z": {
            "sp": 0.31057533969998463,
            "kb": 0.310575339699983,
            "jockey": 0.02715365070763822,
            "combined": 0.2772316115832375,
            "norm_method": "z"
          },
          "source": {
            "kichiuma_fp_url": "https://www.kichiuma-chiho.net/php/search.php?race_id=202605040732&date=2026%2F5%2F4&no=7&id=32&p=fp",
            "nar_table_url": "https://nar.k-ba.net/table.php?date=20260504&track=32&number=7&condition=1",
            "nar_condition": "1"
          }
        },
        {
          "mark": "☆",
          "umaban": 3,
          "name": "アウストラリス",
          "score": 52.39,
          "sp": 62.5,
          "base_index": 96.0,
          "jockey": "加茂飛",
          "jockey_add": 3.3999999999999995,
          "z": {
            "sp": 0.31057533969998463,
            "kb": 0.310575339699983,
            "jockey": -0.29808224023085567,
            "combined": 0.23896856559047353,
            "norm_method": "z"
          },
          "source": {
            "kichiuma_fp_url": "https://www.kichiuma-chiho.net/php/search.php?race_id=202605040732&date=2026%2F5%2F4&no=7&id=32&p=fp",
            "nar_table_url": "https://nar.k-ba.net/table.php?date=20260504&track=32&number=7&condition=1",
            "nar_condition": "1"
          }
        }
      ],
      "konsen": {
        "name": "混戦度",
        "value": 9.7,
        "is_focus": false,
        "gap12": 12.29,
        "gap15": 15.37,
        "gap12_mid": 0.8,
        "gap15_mid": 3.0,
        "focus_th": 30.0,
        "sc12": 0.0611,
        "sc15": 0.1633
      }
    },
    {
      "race_no": 8,
      "race_name": "みどりの日賞Ｂ-３組",
      "picks": [
        {
          "mark": "◎",
          "umaban": 9,
          "name": "ウイントールキン",
          "score": 61.28,
          "sp": 69.6,
          "base_index": 112.0,
          "jockey": "石川慎",
          "jockey_add": 6.865,
          "z": {
            "sp": 1.1457328235769921,
            "kb": 1.0770760453304093,
            "jockey": 1.1643437850355143,
            "combined": 1.127729178381941,
            "norm_method": "z"
          },
          "source": {
            "kichiuma_fp_url": "https://www.kichiuma-chiho.net/php/search.php?race_id=202605040832&date=2026%2F5%2F4&no=8&id=32&p=fp",
            "nar_table_url": "https://nar.k-ba.net/table.php?date=20260504&track=32&number=8&condition=1",
            "nar_condition": "1"
          }
        },
        {
          "mark": "〇",
          "umaban": 3,
          "name": "ジャズダンス",
          "score": 58.99,
          "sp": 67.7,
          "base_index": 107.0,
          "jockey": "山口勲",
          "jockey_add": 8.65,
          "z": {
            "sp": 0.8467838096848692,
            "kb": 0.5385380226652047,
            "jockey": 2.0625175401471316,
            "combined": 0.8991507817922929,
            "norm_method": "z"
          },
          "source": {
            "kichiuma_fp_url": "https://www.kichiuma-chiho.net/php/search.php?race_id=202605040832&date=2026%2F5%2F4&no=8&id=32&p=fp",
            "nar_table_url": "https://nar.k-ba.net/table.php?date=20260504&track=32&number=8&condition=1",
            "nar_condition": "1"
          }
        },
        {
          "mark": "▲",
          "umaban": 5,
          "name": "グシチャンノホシ",
          "score": 58.78,
          "sp": 67.4,
          "base_index": 111.0,
          "jockey": "飛田愛",
          "jockey_add": 6.625,
          "z": {
            "sp": 0.7995813338071658,
            "kb": 0.9693684407973684,
            "jockey": 1.0435809272053809,
            "combined": 0.8782245527334861,
            "norm_method": "z"
          },
          "source": {
            "kichiuma_fp_url": "https://www.kichiuma-chiho.net/php/search.php?race_id=202605040832&date=2026%2F5%2F4&no=8&id=32&p=fp",
            "nar_table_url": "https://nar.k-ba.net/table.php?date=20260504&track=32&number=8&condition=1",
            "nar_condition": "1"
          }
        },
        {
          "mark": "△",
          "umaban": 6,
          "name": "ミスファントム",
          "score": 55.63,
          "sp": 66.1,
          "base_index": 109.0,
          "jockey": "竹吉徹",
          "jockey_add": 4.405,
          "z": {
            "sp": 0.5950372716704473,
            "kb": 0.7539532317312866,
            "jockey": -0.07347550772335316,
            "combined": 0.5631286976420118,
            "norm_method": "z"
          },
          "source": {
            "kichiuma_fp_url": "https://www.kichiuma-chiho.net/php/search.php?race_id=202605040832&date=2026%2F5%2F4&no=8&id=32&p=fp",
            "nar_table_url": "https://nar.k-ba.net/table.php?date=20260504&track=32&number=8&condition=1",
            "nar_condition": "1"
          }
        },
        {
          "mark": "☆",
          "umaban": 11,
          "name": "プアラニ",
          "score": 54.94,
          "sp": 65.8,
          "base_index": 109.0,
          "jockey": "田中純",
          "jockey_add": 3.70125,
          "z": {
            "sp": 0.547834795792744,
            "kb": 0.7539532317312866,
            "jockey": -0.42758742938150496,
            "combined": 0.4937023092835801,
            "norm_method": "z"
          },
          "source": {
            "kichiuma_fp_url": "https://www.kichiuma-chiho.net/php/search.php?race_id=202605040832&date=2026%2F5%2F4&no=8&id=32&p=fp",
            "nar_table_url": "https://nar.k-ba.net/table.php?date=20260504&track=32&number=8&condition=1",
            "nar_condition": "1"
          }
        }
      ],
      "konsen": {
        "name": "混戦度",
        "value": 28.1,
        "is_focus": false,
        "gap12": 2.29,
        "gap15": 6.34,
        "gap12_mid": 0.8,
        "gap15_mid": 3.0,
        "focus_th": 30.0,
        "sc12": 0.2589,
        "sc15": 0.3212
      }
    },
    {
      "race_no": 9,
      "race_name": "メイ特選Ｃ１",
      "picks": [
        {
          "mark": "◎",
          "umaban": 3,
          "name": "テイラーテソーロ",
          "score": 61.36,
          "sp": 65.2,
          "base_index": 103.0,
          "jockey": "山口勲",
          "jockey_add": 8.65,
          "z": {
            "sp": 1.190522524543585,
            "kb": 0.7411971429656457,
            "jockey": 1.8517888310244253,
            "combined": 1.136164036606643,
            "norm_method": "z"
          },
          "source": {
            "kichiuma_fp_url": "https://www.kichiuma-chiho.net/php/search.php?race_id=202605040932&date=2026%2F5%2F4&no=9&id=32&p=fp",
            "nar_table_url": "https://nar.k-ba.net/table.php?date=20260504&track=32&number=9&condition=1",
            "nar_condition": "1"
          }
        },
        {
          "mark": "〇",
          "umaban": 8,
          "name": "ロトエンペラー",
          "score": 59.28,
          "sp": 65.8,
          "base_index": 96.0,
          "jockey": "石川慎",
          "jockey_add": 6.865,
          "z": {
            "sp": 1.363976137390993,
            "kb": -0.009752593986390355,
            "jockey": 1.0914202789990255,
            "combined": 0.927872880116237,
            "norm_method": "z"
          },
          "source": {
            "kichiuma_fp_url": "https://www.kichiuma-chiho.net/php/search.php?race_id=202605040932&date=2026%2F5%2F4&no=9&id=32&p=fp",
            "nar_table_url": "https://nar.k-ba.net/table.php?date=20260504&track=32&number=9&condition=1",
            "nar_condition": "1"
          }
        },
        {
          "mark": "▲",
          "umaban": 5,
          "name": "セプトラム",
          "score": 58.37,
          "sp": 64.5,
          "base_index": 105.0,
          "jockey": "金山昇",
          "jockey_add": 3.8012500000000005,
          "z": {
            "sp": 0.9881599762216067,
            "kb": 0.9557542106662275,
            "jockey": -0.2136660802546544,
            "combined": 0.8372375679434056,
            "norm_method": "z"
          },
          "source": {
            "kichiuma_fp_url": "https://www.kichiuma-chiho.net/php/search.php?race_id=202605040932&date=2026%2F5%2F4&no=9&id=32&p=fp",
            "nar_table_url": "https://nar.k-ba.net/table.php?date=20260504&track=32&number=9&condition=1",
            "nar_condition": "1"
          }
        },
        {
          "mark": "△",
          "umaban": 6,
          "name": "ポムヴェルト",
          "score": 55.35,
          "sp": 62.3,
          "base_index": 108.0,
          "jockey": "田中直",
          "jockey_add": 3.3449999999999998,
          "z": {
            "sp": 0.3521633957811043,
            "kb": 1.2775898122171,
            "jockey": -0.40801798605946626,
            "combined": 0.5349145321633889,
            "norm_method": "z"
          },
          "source": {
            "kichiuma_fp_url": "https://www.kichiuma-chiho.net/php/search.php?race_id=202605040932&date=2026%2F5%2F4&no=9&id=32&p=fp",
            "nar_table_url": "https://nar.k-ba.net/table.php?date=20260504&track=32&number=9&condition=1",
            "nar_condition": "1"
          }
        },
        {
          "mark": "☆",
          "umaban": 9,
          "name": "スティルザワン",
          "score": 52.56,
          "sp": 61.7,
          "base_index": 101.0,
          "jockey": "山下裕",
          "jockey_add": 4.22,
          "z": {
            "sp": 0.17870978293369644,
            "kb": 0.526640075265064,
            "jockey": -0.035288303694074194,
            "combined": 0.2558659763690668,
            "norm_method": "z"
          },
          "source": {
            "kichiuma_fp_url": "https://www.kichiuma-chiho.net/php/search.php?race_id=202605040932&date=2026%2F5%2F4&no=9&id=32&p=fp",
            "nar_table_url": "https://nar.k-ba.net/table.php?date=20260504&track=32&number=9&condition=1",
            "nar_condition": "1"
          }
        }
      ],
      "konsen": {
        "name": "混戦度",
        "value": 27.0,
        "is_focus": false,
        "gap12": 2.08,
        "gap15": 8.8,
        "gap12_mid": 0.8,
        "gap15_mid": 3.0,
        "focus_th": 30.0,
        "sc12": 0.2778,
        "sc15": 0.2542
      }
    },
    {
      "race_no": 10,
      "race_name": "シャイニングスター特別３歳",
      "picks": [
        {
          "mark": "◎",
          "umaban": 8,
          "name": "サイオウガウマ",
          "score": 62.5,
          "sp": 69.0,
          "base_index": 118.0,
          "jockey": "林悠翔",
          "jockey_add": 3.61125,
          "z": {
            "sp": 1.3035464327593322,
            "kb": 1.7128971552496588,
            "jockey": -0.1748266286542934,
            "combined": 1.2500174615607662,
            "norm_method": "z"
          },
          "source": {
            "kichiuma_fp_url": "https://www.kichiuma-chiho.net/php/search.php?race_id=202605041032&date=2026%2F5%2F4&no=10&id=32&p=fp",
            "nar_table_url": "https://nar.k-ba.net/table.php?date=20260504&track=32&number=10&condition=1",
            "nar_condition": "1"
          }
        },
        {
          "mark": "〇",
          "umaban": 3,
          "name": "カシノフレックス",
          "score": 61.51,
          "sp": 73.2,
          "base_index": 107.0,
          "jockey": "田中直",
          "jockey_add": 3.3449999999999998,
          "z": {
            "sp": 1.7571417117642365,
            "kb": 0.5127781292785605,
            "jockey": -0.28675350543026146,
            "combined": 1.1506941619514497,
            "norm_method": "z"
          },
          "source": {
            "kichiuma_fp_url": "https://www.kichiuma-chiho.net/php/search.php?race_id=202605041032&date=2026%2F5%2F4&no=10&id=32&p=fp",
            "nar_table_url": "https://nar.k-ba.net/table.php?date=20260504&track=32&number=10&condition=1",
            "nar_condition": "1"
          }
        },
        {
          "mark": "▲",
          "umaban": 2,
          "name": "ニシノガウェイン",
          "score": 55.47,
          "sp": 65.5,
          "base_index": 98.0,
          "jockey": "石川慎",
          "jockey_add": 6.865,
          "z": {
            "sp": 0.9255503669219122,
            "kb": -0.46913743742506536,
            "jockey": 1.1929933725092956,
            "combined": 0.5468119545360227,
            "norm_method": "z"
          },
          "source": {
            "kichiuma_fp_url": "https://www.kichiuma-chiho.net/php/search.php?race_id=202605041032&date=2026%2F5%2F4&no=10&id=32&p=fp",
            "nar_table_url": "https://nar.k-ba.net/table.php?date=20260504&track=32&number=10&condition=1",
            "nar_condition": "1"
          }
        },
        {
          "mark": "△",
          "umaban": 1,
          "name": "テイエムパイロダン",
          "score": 52.68,
          "sp": 57.2,
          "base_index": 103.0,
          "jockey": "山口勲",
          "jockey_add": 8.65,
          "z": {
            "sp": 0.029159696507459223,
            "kb": 0.07637121074361565,
            "jockey": 1.943376377373531,
            "combined": 0.2682473984435137,
            "norm_method": "z"
          },
          "source": {
            "kichiuma_fp_url": "https://www.kichiuma-chiho.net/php/search.php?race_id=202605041032&date=2026%2F5%2F4&no=10&id=32&p=fp",
            "nar_table_url": "https://nar.k-ba.net/table.php?date=20260504&track=32&number=10&condition=1",
            "nar_condition": "1"
          }
        },
        {
          "mark": "☆",
          "umaban": 10,
          "name": "マジックアロマ",
          "score": 49.11,
          "sp": 52.4,
          "base_index": 109.0,
          "jockey": "田中純",
          "jockey_add": 3.70125,
          "z": {
            "sp": -0.4892349080695744,
            "kb": 0.7309815885460329,
            "jockey": -0.13699219143424798,
            "combined": -0.08890738357847504,
            "norm_method": "z"
          },
          "source": {
            "kichiuma_fp_url": "https://www.kichiuma-chiho.net/php/search.php?race_id=202605041032&date=2026%2F5%2F4&no=10&id=32&p=fp",
            "nar_table_url": "https://nar.k-ba.net/table.php?date=20260504&track=32&number=10&condition=1",
            "nar_condition": "1"
          }
        }
      ],
      "konsen": {
        "name": "混戦度",
        "value": 35.5,
        "is_focus": true,
        "gap12": 0.99,
        "gap15": 13.39,
        "gap12_mid": 0.8,
        "gap15_mid": 3.0,
        "focus_th": 30.0,
        "sc12": 0.4469,
        "sc15": 0.183
      }
    },
    {
      "race_no": 11,
      "race_name": "ＹｏｕＴｕｂｅ生配信中！ＳＡＧＡリベンジャーズジョッキーズＣ２-１１組",
      "picks": [
        {
          "mark": "◎",
          "umaban": 3,
          "name": "ヘキレキイッセン",
          "score": 64.52,
          "sp": 62.3,
          "base_index": 84.5,
          "jockey": "田中直",
          "jockey_add": 3.3449999999999998,
          "z": {
            "sp": 2.467344380499928,
            "kb": 0.13967428343851815,
            "jockey": -0.34243348684157493,
            "combined": 1.452173426382866,
            "norm_method": "z"
          },
          "source": {
            "kichiuma_fp_url": "https://www.kichiuma-chiho.net/php/search.php?race_id=202605041132&date=2026%2F5%2F4&no=11&id=32&p=fp",
            "nar_table_url": "https://nar.k-ba.net/table.php?date=20260504&track=32&number=11&condition=1",
            "nar_condition": "1"
          }
        },
        {
          "mark": "〇",
          "umaban": 7,
          "name": "ブレイズボーイ",
          "score": 60.85,
          "sp": 53.7,
          "base_index": 93.0,
          "jockey": "山口勲",
          "jockey_add": 8.65,
          "z": {
            "sp": 0.49096183693267215,
            "kb": 1.590734894716466,
            "jockey": 2.7939535839279097,
            "combined": 1.0853647065155807,
            "norm_method": "z"
          },
          "source": {
            "kichiuma_fp_url": "https://www.kichiuma-chiho.net/php/search.php?race_id=202605041132&date=2026%2F5%2F4&no=11&id=32&p=fp",
            "nar_table_url": "https://nar.k-ba.net/table.php?date=20260504&track=32&number=11&condition=1",
            "nar_condition": "1"
          }
        },
        {
          "mark": "▲",
          "umaban": 9,
          "name": "クイーンパレス",
          "score": 55.88,
          "sp": 54.0,
          "base_index": 89.0,
          "jockey": "金山昇",
          "jockey_add": 3.8012500000000005,
          "z": {
            "sp": 0.5599054140338549,
            "kb": 0.9078828423503729,
            "jockey": -0.07269237448746003,
            "combined": 0.5878284472420878,
            "norm_method": "z"
          },
          "source": {
            "kichiuma_fp_url": "https://www.kichiuma-chiho.net/php/search.php?race_id=202605041132&date=2026%2F5%2F4&no=11&id=32&p=fp",
            "nar_table_url": "https://nar.k-ba.net/table.php?date=20260504&track=32&number=11&condition=1",
            "nar_condition": "1"
          }
        },
        {
          "mark": "△",
          "umaban": 10,
          "name": "ホウオウギフト",
          "score": 52.2,
          "sp": 53.4,
          "base_index": 85.0,
          "jockey": "中山蓮",
          "jockey_add": 2.5650000000000004,
          "z": {
            "sp": 0.4220182598314878,
            "kb": 0.22503078998427978,
            "jockey": -0.8035799364551839,
            "combined": 0.21989274560740643,
            "norm_method": "z"
          },
          "source": {
            "kichiuma_fp_url": "https://www.kichiuma-chiho.net/php/search.php?race_id=202605041132&date=2026%2F5%2F4&no=11&id=32&p=fp",
            "nar_table_url": "https://nar.k-ba.net/table.php?date=20260504&track=32&number=11&condition=1",
            "nar_condition": "1"
          }
        },
        {
          "mark": "☆",
          "umaban": 1,
          "name": "スマートアクシオン",
          "score": 49.18,
          "sp": 49.2,
          "base_index": 88.0,
          "jockey": "山下裕",
          "jockey_add": 4.22,
          "z": {
            "sp": -0.5431918195850788,
            "kb": 0.7371698292588496,
            "jockey": 0.17487823548138431,
            "combined": -0.08213603403492772,
            "norm_method": "z"
          },
          "source": {
            "kichiuma_fp_url": "https://www.kichiuma-chiho.net/php/search.php?race_id=202605041132&date=2026%2F5%2F4&no=11&id=32&p=fp",
            "nar_table_url": "https://nar.k-ba.net/table.php?date=20260504&track=32&number=11&condition=1",
            "nar_condition": "1"
          }
        }
      ],
      "konsen": {
        "name": "混戦度",
        "value": 17.4,
        "is_focus": false,
        "gap12": 3.67,
        "gap15": 15.34,
        "gap12_mid": 0.8,
        "gap15_mid": 3.0,
        "focus_th": 30.0,
        "sc12": 0.179,
        "sc15": 0.1636
      }
    }
  ],
  "generated_at": "2026-05-03T12:32:36",
  "weights": {
    "SP_W": 1.0,
    "KB_W": 0.5,
    "JOCKEY_W": 0.2
  },
  "scoring": {
    "method": "zscore_composite",
    "norm_method": "z",
    "score_base": 50.0,
    "score_scale": 10.0,
    "notes": "SP/KB/騎手をレース内で標準化（Z化）し、欠損は推定 or レース中央値で補完して合成"
  },
  "konsen_config": {
    "enabled": true,
    "name": "混戦度",
    "gap12_mid": 0.8,
    "gap15_mid": 3.0,
    "focus_th": 30.0
  },
  "source": {
    "kaisekisya_url": "https://www.kaisekisya.net/local/jockey/saga.html",
    "nar_base": "https://nar.k-ba.net/"
  }
}